topsis/__init__.py
topsis/topsis.py
topsis_raj_102303324-0.1.8.dist-info/METADATA
topsis_raj_102303324-0.1.8.dist-info/WHEEL
topsis_raj_102303324-0.1.8.dist-info/entry_points.txt
topsis_raj_102303324-0.1.8.dist-info/top_level.txt
topsis_raj_102303324-0.1.8.dist-info/RECORD
