Metadata-Version: 2.4
Name: Topsis-raj-102303324
Version: 0.1.8
Summary: TOPSIS implementation using Python
Author: Raj Gupta
Requires-Python: >=3.7
Requires-Dist: pandas
Requires-Dist: numpy
Dynamic: author
Dynamic: description
Dynamic: description-content-type
Dynamic: requires-dist
Dynamic: requires-python
Dynamic: summary
